yafowil.widget.dict-1.9-py3.9-nspkg.pth
yafowil/widget/dict/__init__.py
yafowil/widget/dict/example.py
yafowil/widget/dict/tests.py
yafowil/widget/dict/widget.py
yafowil/widget/dict/locales/yafowil.widget.dict.pot
yafowil/widget/dict/locales/de/LC_MESSAGES/yafowil.widget.dict.po
yafowil/widget/dict/locales/en/LC_MESSAGES/yafowil.widget.dict.po
yafowil/widget/dict/resources/widget.js
yafowil/widget/dict/resources/bootstrap/widget.css
yafowil/widget/dict/resources/default/widget.css
yafowil/widget/dict/resources/default/images/icon_add.png
yafowil/widget/dict/resources/default/images/icon_down.png
yafowil/widget/dict/resources/default/images/icon_down_disabled.png
yafowil/widget/dict/resources/default/images/icon_remove.png
yafowil/widget/dict/resources/default/images/icon_up.png
yafowil/widget/dict/resources/default/images/icon_up_disabled.png
yafowil/widget/dict/resources/plone5/widget.css
yafowil_widget_dict-1.9.dist-info/licenses/LICENSE.rst
yafowil_widget_dict-1.9.dist-info/METADATA
yafowil_widget_dict-1.9.dist-info/WHEEL
yafowil_widget_dict-1.9.dist-info/entry_points.txt
yafowil_widget_dict-1.9.dist-info/namespace_packages.txt
yafowil_widget_dict-1.9.dist-info/top_level.txt
yafowil_widget_dict-1.9.dist-info/RECORD
